clsar/__init__.py
clsar/main.py
clsar/dataset/__init__.py
clsar/dataset/data.py
clsar/feature/__init__.py
clsar/feature/featurizer.py
clsar/model/__init__.py
clsar/model/loss.py
clsar/model/loss_tf.py
clsar/model/model.py
clsar/model/saver.py
clsar/model/train.py
clsar-2.0.0.dist-info/LICENSE.txt
clsar-2.0.0.dist-info/METADATA
clsar-2.0.0.dist-info/WHEEL
clsar-2.0.0.dist-info/top_level.txt
clsar-2.0.0.dist-info/RECORD
