Metadata-Version: 2.1
Name: clsar
Version: 2.0.0
Summary: Activity Cliff-Informed Contrastive Learning for Molecular Property Prediction
Home-page: https://github.com/shenwanxiang/ACANet/tree/main
Author: WanXiang Shen
License-File: LICENSE.txt
Requires-Dist: torch
Requires-Dist: torch-geometric
Requires-Dist: numpy
Requires-Dist: pandas
Requires-Dist: seaborn
Requires-Dist: rdkit
Requires-Dist: Levenshtein
Provides-Extra: dev
Requires-Dist: pytest; extra == "dev"
